fastdeploy/__init__.py
fastdeploy/__main__.py
fastdeploy/download.py
fastdeploy_py3-0.1.0.dist-info/LICENSE
fastdeploy_py3-0.1.0.dist-info/METADATA
fastdeploy_py3-0.1.0.dist-info/WHEEL
fastdeploy_py3-0.1.0.dist-info/entry_points.txt
fastdeploy_py3-0.1.0.dist-info/top_level.txt
fastdeploy_py3-0.1.0.dist-info/RECORD
