Metadata-Version: 2.1
Name: fastdeploy-py3
Version: 0.1.0
Summary: FastDeploy is a toolkit to deploy deeplearning models.
Home-page: https://github.com/PaddlePaddle/FastDeploy
Author: FastDeploy
Author-email: fastdeploy@baidu.com
License: Apache 2.0
Platform: UNKNOWN
Classifier: Programming Language :: Python :: 3
Classifier: License :: OSI Approved :: Apache Software License
Classifier: Operating System :: OS Independent
Requires-Dist: tqdm
Requires-Dist: six
Provides-Extra: vision-cpu
Requires-Dist: fastdeploy-vision-cpu ; extra == 'vision-cpu'
Provides-Extra: vision-gpu
Requires-Dist: fastdeploy-vision-gpu ; extra == 'vision-gpu'
